README.rst
setup.cfg
setup.py
rrsm/__init__.py
rrsm/core.py
rrsm.egg-info/PKG-INFO
rrsm.egg-info/SOURCES.txt
rrsm.egg-info/dependency_links.txt
rrsm.egg-info/top_level.txt