Metadata-Version: 1.1
Name: rrsm
Version: 0.2.0
Summary: Readable run-time state machine
Home-page: https://github.com/jnmclarty/rrsm
Author: Jeffrey McLarty
Author-email: jeffrey.mclarty@gmail.com
License: UNKNOWN
Download-URL: https://github.com/jnmclarty/rrsm/tarball/0.2.0
Keywords: readable,runtime,run-time,finite,state,machine
Platform: UNKNOWN
Classifier: Development Status :: 1 - Planning
Classifier: License :: OSI Approved :: MIT License
Classifier: Intended Audience :: Developers
Classifier: Operating System :: OS Independent
Classifier: Programming Language :: Python :: 2.6
Classifier: Programming Language :: Python :: 2.7
Classifier: Programming Language :: Python :: 3.3
Classifier: Programming Language :: Python :: 3.4
